timetables/parser/edupage/__init__.py
timetables/parser/edupage/api/__init__.py
timetables/parser/edupage/api/api.py
timetables/parser/edupage/api/api_v1.py
timetables/parser/edupage/api/api_v2.py
timetables/parser/edupage/api/const.py
timetables/parser/edupage/api/model/__init__.py
timetables/parser/edupage/api/model/account.py
timetables/parser/edupage/api/model/edupage.py
timetables/parser/edupage/api/model/exception.py
timetables/parser/edupage/api/model/portal.py
timetables/parser/edupage/api/model/session.py
timetables/parser/edupage/api/utils.py
timetables/parser/edupage/cli.py
timetables/parser/edupage/parser.py
timetables_parser_edupage-1.0.0.dist-info/entry_points.txt
timetables_parser_edupage-1.0.0.dist-info/WHEEL
timetables_parser_edupage-1.0.0.dist-info/METADATA
timetables_parser_edupage-1.0.0.dist-info/RECORD
