Metadata-Version: 2.1
Name: timetables-parser-edupage
Version: 1.0.0
Summary: Edupage.org timetable parser library
Author: Kuba Szczodrzyński
Author-email: kuba@szczodrzynski.pl
Requires-Python: >=3.10,<4.0
Classifier: Programming Language :: Python :: 3
Classifier: Programming Language :: Python :: 3.10
Requires-Dist: aiohttp[speedups] (>=3.8.0,<4.0.0)
Requires-Dist: beautifulsoup4 (>=4.10.0,<5.0.0)
Requires-Dist: pydantic (>=1.8.2,<2.0.0)
Requires-Dist: timetables-lib (>=1.0.0,<2.0.0)
